pybackground/__init__.py
pybackground/scheduler.py
pybackground/task.py
PyBackground-0.1.2.dist-info/LICENSE
PyBackground-0.1.2.dist-info/METADATA
PyBackground-0.1.2.dist-info/WHEEL
PyBackground-0.1.2.dist-info/top_level.txt
PyBackground-0.1.2.dist-info/RECORD
