Metadata-Version: 2.1
Name: PyBackground
Version: 0.1.2
Summary: A lightweight scheduler that runs tasks in the background
Home-page: https://github.com/yzhang-dev/PyBackground
Author: Yi Zhang
Author-email: yizhang.dev@gmail.com
License: MIT
Download-URL: https://github.com/yzhang-dev/PyBackground
Keywords: background-jobs,background-thread,tasks,background
Platform: UNKNOWN
Classifier: License :: OSI Approved :: MIT License
Classifier: Operating System :: OS Independent
Classifier: Programming Language :: Python :: 3
Classifier: Programming Language :: Python :: 3.7
Requires-Python: >=3.7
